langchain_writer/__init__.py
langchain_writer/base.py
langchain_writer/chat_models.py
langchain_writer/pdf_parser.py
langchain_writer/py.typed
langchain_writer/text_splitter.py
langchain_writer/tools.py
langchain_writer-0.3.4.dist-info/LICENSE
langchain_writer-0.3.4.dist-info/METADATA
langchain_writer-0.3.4.dist-info/WHEEL
langchain_writer-0.3.4.dist-info/RECORD
