Metadata-Version: 2.3
Name: langchain-writer
Version: 0.3.4
Summary: An integration package connecting Writer and LangChain
License: MIT
Author: Writer, Inc.
Author-email: dev-feedback@writer.com
Requires-Python: >=3.10,<4.0
Classifier: License :: OSI Approved :: MIT License
Classifier: Programming Language :: Python :: 3
Classifier: Programming Language :: Python :: 3.10
Classifier: Programming Language :: Python :: 3.11
Classifier: Programming Language :: Python :: 3.12
Classifier: Programming Language :: Python :: 3.13
Requires-Dist: langchain-core (>=0.3.76,<0.4.0)
Requires-Dist: langchain-text-splitters (>=0.3.5,<0.4.0)
Requires-Dist: writer-sdk (>=2.3.0,<3.0)
Project-URL: Documentation, https://dev.writer.com
Project-URL: Homepage, https://www.writer.com
Project-URL: Repository, https://github.com/writer/langchain-writer
